{
    "type": "FeatureCollection",
    "features": [
        {
            "type": "Feature",
            "geometry": {
                "type": "MultiPolygon",
                "coordinates": [
                    [
                        [
                            [
                                120.30338040007,
                                22.636640364127
                            ],
                            [
                                120.31371570221,
                                22.636739072859
                            ],
                            [
                                120.31674527936,
                                22.634395208851
                            ],
                            [
                                120.31806983834,
                                22.630117306437
                            ],
                            [
                                120.31320417595,
                                22.630555198091
                            ],
                            [
                                120.31415837387,
                                22.627442543174
                            ],
                            [
                                120.31088150582,
                                22.626386786028
                            ],
                            [
                                120.3120232906,
                                22.6232149321
                            ],
                            [
                                120.302152968,
                                22.620018302384
                            ],
                            [
                                120.30147469528,
                                22.627222831032
                            ],
                            [
                                120.29818245177,
                                22.626145016324
                            ],
                            [
                                120.29753705631,
                                22.627817411184
                            ],
                            [
                                120.29992494956,
                                22.628618603891
                            ],
                            [
                                120.29702194903,
                                22.636079790828
                            ],
                            [
                                120.30338040007,
                                22.636640364127
                            ]
                        ]
                    ]
                ]
            },
            "properties": {
                "id": "55085a31-843c-40fa-b5ef-3584acb5b862",
                "parent_id": "55085a25-9fd8-4e35-91b2-3584acb5b862",
                "name": "新興區",
                "lft": "26579",
                "rght": "26644",
                "is_area": true,
                "ivid": "KHH-060",
                "code": "64000060",
                "population": "52624",
                "population_electors": "44179",
                "keywords": "2016,高雄市,新興區"
            }
        },
        {
            "type": "Feature",
            "geometry": {
                "type": "MultiPolygon",
                "coordinates": [
                    [
                        [
                            [
                                120.29753705631,
                                22.627817411184
                            ],
                            [
                                120.29818245177,
                                22.626145016324
                            ],
                            [
                                120.30147469528,
                                22.627222831032
                            ],
                            [
                                120.302152968,
                                22.620018302384
                            ],
                            [
                                120.29621622048,
                                22.618009595865
                            ],
                            [
                                120.29505765189,
                                22.621100306986
                            ],
                            [
                                120.29017507285,
                                22.620624962851
                            ],
                            [
                                120.28593724018,
                                22.631707915945
                            ],
                            [
                                120.29702194903,
                                22.636079790828
                            ],
                            [
                                120.29992494956,
                                22.628618603891
                            ],
                            [
                                120.29753705631,
                                22.627817411184
                            ]
                        ]
                    ]
                ]
            },
            "properties": {
                "id": "55085a33-2448-42ab-af56-3584acb5b862",
                "parent_id": "55085a25-9fd8-4e35-91b2-3584acb5b862",
                "name": "前金區",
                "lft": "26645",
                "rght": "26686",
                "is_area": true,
                "ivid": "KHH-070",
                "code": "64000070",
                "population": "27869",
                "population_electors": "24024",
                "keywords": "2016,高雄市,前金區"
            }
        },
        {
            "type": "Feature",
            "geometry": {
                "type": "MultiPolygon",
                "coordinates": [
                    [
                        [
                            [
                                120.317718541,
                                22.638612521942
                            ],
                            [
                                120.3446539199,
                                22.63389693159
                            ],
                            [
                                120.34310116296,
                                22.630938419936
                            ],
                            [
                                120.33934762989,
                                22.629530013082
                            ],
                            [
                                120.34444951729,
                                22.628164727071
                            ],
                            [
                                120.34434562563,
                                22.624879370524
                            ],
                            [
                                120.34001477521,
                                22.624243006628
                            ],
                            [
                                120.33817795362,
                                22.620611856349
                            ],
                            [
                                120.34064827819,
                                22.619050677534
                            ],
                            [
                                120.33948450854,
                                22.617677733549
                            ],
                            [
                                120.33487040214,
                                22.616103129699
                            ],
                            [
                                120.33451639223,
                                22.618479003881
                            ],
                            [
                                120.32788352019,
                                22.61767471561
                            ],
                            [
                                120.32667484858,
                                22.611720327594
                            ],
                            [
                                120.32502753027,
                                22.611927783449
                            ],
                            [
                                120.32521819319,
                                22.614914832789
                            ],
                            [
                                120.31816330562,
                                22.615358956776
                            ],
                            [
                                120.31770255816,
                                22.618275171665
                            ],
                            [
                                120.30449156129,
                                22.613906116773
                            ],
                            [
                                120.30510571981,
                                22.612403838404
                            ],
                            [
                                120.29635795972,
                                22.609061604113
                            ],
                            [
                                120.29000577871,
                                22.612187592215
                            ],
                            [
                                120.29275939215,
                                22.617306773971
                            ],
                            [
                                120.29017507285,
                                22.620624962851
                            ],
                            [
                                120.29505765189,
                                22.621100306986
                            ],
                            [
                                120.29621622048,
                                22.618009595865
                            ],
                            [
                                120.3120232906,
                                22.6232149321
                            ],
                            [
                                120.31088150582,
                                22.626386786028
                            ],
                            [
                                120.31415837387,
                                22.627442543174
                            ],
                            [
                                120.31320417595,
                                22.630555198091
                            ],
                            [
                                120.31806983834,
                                22.630117306437
                            ],
                            [
                                120.31674527936,
                                22.634395208851
                            ],
                            [
                                120.32078975681,
                                22.632222154602
                            ],
                            [
                                120.31882157169,
                                22.637204099202
                            ],
                            [
                                120.31666295092,
                                22.638615658823
                            ],
                            [
                                120.317718541,
                                22.638612521942
                            ]
                        ]
                    ]
                ]
            },
            "properties": {
                "id": "55085a34-0b94-40e3-8c67-3584acb5b862",
                "parent_id": "55085a25-9fd8-4e35-91b2-3584acb5b862",
                "name": "苓雅區",
                "lft": "26687",
                "rght": "26826",
                "is_area": true,
                "ivid": "KHH-080",
                "code": "64000080",
                "population": "176033",
                "population_electors": "146130",
                "keywords": "2016,高雄市,苓雅區"
            }
        },
        {
            "type": "Feature",
            "geometry": {
                "type": "MultiPolygon",
                "coordinates": [
                    [
                        [
                            [
                                120.32363088081,
                                22.614471358011
                            ],
                            [
                                120.32521826902,
                                22.614914834989
                            ],
                            [
                                120.32502760617,
                                22.611927785651
                            ],
                            [
                                120.32243855542,
                                22.612039011738
                            ],
                            [
                                120.32253278186,
                                22.61541269562
                            ],
                            [
                                120.32363088081,
                                22.614471358011
                            ]
                        ]
                    ]
                ]
            },
            "properties": {
                "id": "55085a3a-0a38-4273-8278-3584acb5b862",
                "parent_id": "55085a38-4898-4e47-a8c6-3584acb5b862",
                "name": "竹北里",
                "lft": "26908",
                "rght": "26909",
                "is_area": true,
                "ivid": "KHH-090-043",
                "code": "64000090-043",
                "population": "2545",
                "population_electors": "2086",
                "keywords": "2016,高雄市,前鎮區,竹北里"
            }
        },
        {
            "type": "Feature",
            "geometry": {
                "type": "MultiPolygon",
                "coordinates": [
                    [
                        [
                            [
                                120.31811924909,
                                22.614843949151
                            ],
                            [
                                120.31795133601,
                                22.612841260368
                            ],
                            [
                                120.3162924005,
                                22.613065020654
                            ],
                            [
                                120.31613072068,
                                22.617748496559
                            ],
                            [
                                120.31770263654,
                                22.618275173902
                            ],
                            [
                                120.31811924909,
                                22.614843949151
                            ]
                        ]
                    ]
                ]
            },
            "properties": {
                "id": "55085a3a-2564-43ce-83c7-3584acb5b862",
                "parent_id": "55085a38-4898-4e47-a8c6-3584acb5b862",
                "name": "復國里",
                "lft": "26900",
                "rght": "26901",
                "is_area": true,
                "ivid": "KHH-090-039",
                "code": "64000090-039",
                "population": "3251",
                "population_electors": "2758",
                "keywords": "2016,高雄市,前鎮區,復國里"
            }
        },
        {
            "type": "Feature",
            "geometry": {
                "type": "MultiPolygon",
                "coordinates": [
                    [
                        [
                            [
                                120.32455692176,
                                22.611994223227
                            ],
                            [
                                120.32686575918,
                                22.611659707724
                            ],
                            [
                                120.32623087097,
                                22.609734318137
                            ],
                            [
                                120.3218333544,
                                22.610183061183
                            ],
                            [
                                120.32243855542,
                                22.612039011738
                            ],
                            [
                                120.32455692176,
                                22.611994223227
                            ]
                        ]
                    ]
                ]
            },
            "properties": {
                "id": "55085a3a-5f98-4ac4-bdd4-3584acb5b862",
                "parent_id": "55085a38-4898-4e47-a8c6-3584acb5b862",
                "name": "竹東里",
                "lft": "26904",
                "rght": "26905",
                "is_area": true,
                "ivid": "KHH-090-041",
                "code": "64000090-041",
                "population": "2601",
                "population_electors": "2218",
                "keywords": "2016,高雄市,前鎮區,竹東里"
            }
        },
        {
            "type": "Feature",
            "geometry": {
                "type": "MultiPolygon",
                "coordinates": [
                    [
                        [
                            [
                                120.32071345197,
                                22.606883590163
                            ],
                            [
                                120.31663090953,
                                22.608554568294
                            ],
                            [
                                120.31795133601,
                                22.612841260368
                            ],
                            [
                                120.32250622357,
                                22.612246520097
                            ],
                            [
                                120.32071345197,
                                22.606883590163
                            ]
                        ]
                    ]
                ]
            },
            "properties": {
                "id": "55085a3a-bb14-481a-a8b5-3584acb5b862",
                "parent_id": "55085a38-4898-4e47-a8c6-3584acb5b862",
                "name": "竹西里",
                "lft": "26910",
                "rght": "26911",
                "is_area": true,
                "ivid": "KHH-090-044",
                "code": "64000090-044",
                "population": "4867",
                "population_electors": "3959",
                "keywords": "2016,高雄市,前鎮區,竹西里"
            }
        },
        {
            "type": "Feature",
            "geometry": {
                "type": "MultiPolygon",
                "coordinates": [
                    [
                        [
                            [
                                120.32020861406,
                                22.606973137579
                            ],
                            [
                                120.32119270664,
                                22.608289654214
                            ],
                            [
                                120.32554512804,
                                22.607600742522
                            ],
                            [
                                120.32473847295,
                                22.605020665931
                            ],
                            [
                                120.32103216623,
                                22.605407060883
                            ],
                            [
                                120.32047544914,
                                22.60389388612
                            ],
                            [
                                120.31597437155,
                                22.606410643014
                            ],
                            [
                                120.31436393651,
                                22.604138263639
                            ],
                            [
                                120.31266123929,
                                22.605670564833
                            ],
                            [
                                120.31655369395,
                                22.608571476488
                            ],
                            [
                                120.32020861406,
                                22.606973137579
                            ]
                        ]
                    ]
                ]
            },
            "properties": {
                "id": "55085a3a-c9bc-4a6b-8208-3584acb5b862",
                "parent_id": "55085a38-4898-4e47-a8c6-3584acb5b862",
                "name": "竹南里",
                "lft": "26906",
                "rght": "26907",
                "is_area": true,
                "ivid": "KHH-090-042",
                "code": "64000090-042",
                "population": "8412",
                "population_electors": "6351",
                "keywords": "2016,高雄市,前鎮區,竹南里"
            }
        },
        {
            "type": "Feature",
            "geometry": {
                "type": "MultiPolygon",
                "coordinates": [
                    [
                        [
                            [
                                120.32253440559,
                                22.615607075275
                            ],
                            [
                                120.32250622357,
                                22.612246520097
                            ],
                            [
                                120.31795133601,
                                22.612841260368
                            ],
                            [
                                120.31816338385,
                                22.615358959011
                            ],
                            [
                                120.32253440559,
                                22.615607075275
                            ]
                        ]
                    ]
                ]
            },
            "properties": {
                "id": "55085a3a-dc24-4867-b9a6-3584acb5b862",
                "parent_id": "55085a38-4898-4e47-a8c6-3584acb5b862",
                "name": "竹中里",
                "lft": "26912",
                "rght": "26913",
                "is_area": true,
                "ivid": "KHH-090-045",
                "code": "64000090-045",
                "population": "3917",
                "population_electors": "3239",
                "keywords": "2016,高雄市,前鎮區,竹中里"
            }
        },
        {
            "type": "Feature",
            "geometry": {
                "type": "MultiPolygon",
                "coordinates": [
                    [
                        [
                            [
                                120.32473077483,
                                22.609939776799
                            ],
                            [
                                120.32623087097,
                                22.609734318137
                            ],
                            [
                                120.32554512804,
                                22.607600742522
                            ],
                            [
                                120.32119270664,
                                22.608289654214
                            ],
                            [
                                120.3218333544,
                                22.610183061183
                            ],
                            [
                                120.32473077483,
                                22.609939776799
                            ]
                        ]
                    ]
                ]
            },
            "properties": {
                "id": "55085a3a-f20c-4409-a12c-3584acb5b862",
                "parent_id": "55085a38-4898-4e47-a8c6-3584acb5b862",
                "name": "竹內里",
                "lft": "26902",
                "rght": "26903",
                "is_area": true,
                "ivid": "KHH-090-040",
                "code": "64000090-040",
                "population": "3195",
                "population_electors": "2664",
                "keywords": "2016,高雄市,前鎮區,竹內里"
            }
        },
        {
            "type": "Feature",
            "geometry": {
                "type": "MultiPolygon",
                "coordinates": [
                    [
                        [
                            [
                                120.31495573141,
                                22.613226679823
                            ],
                            [
                                120.31795133601,
                                22.612841260368
                            ],
                            [
                                120.31663090953,
                                22.608554568294
                            ],
                            [
                                120.31313420031,
                                22.610080039551
                            ],
                            [
                                120.31495573141,
                                22.613226679823
                            ]
                        ]
                    ]
                ]
            },
            "properties": {
                "id": "55085a3a-ff70-438d-be6c-3584acb5b862",
                "parent_id": "55085a38-4898-4e47-a8c6-3584acb5b862",
                "name": "興東里",
                "lft": "26896",
                "rght": "26897",
                "is_area": true,
                "ivid": "KHH-090-037",
                "code": "64000090-037",
                "population": "6277",
                "population_electors": "5018",
                "keywords": "2016,高雄市,前鎮區,興東里"
            }
        }
    ],
    "properties": {
        "election_id": "55086646-73b0-4839-860d-2f916ab936af",
        "election": "2016-01 > 立法委員 > 高雄市 > 第07選區[區域]",
        "candidates": [
            {
                "id": "550c640c-16f8-4bb8-9ce8-025cacb5b862",
                "stage": "2",
                "name": "趙天麟",
                "party": "民主進步黨"
            },
            {
                "id": "555b4ec8-c2f8-456c-a94b-5a316ab936af",
                "stage": "1",
                "name": "莊啟旺",
                "party": "中國國民黨"
            },
            {
                "id": "56594363-d78c-4163-ac29-197f6ab936af",
                "stage": "1",
                "name": "林景元",
                "party": "無"
            },
            {
                "id": "565943c3-2df4-426b-9e0e-197f6ab936af",
                "stage": "1",
                "name": "陳惠敏",
                "party": "時代力量"
            },
            {
                "id": "565943da-d6a0-491d-bfc6-19786ab936af",
                "stage": "1",
                "name": "陳素莉",
                "party": "和平鴿聯盟黨"
            }
        ]
    }
}